{"title":"Harvard_Manchester_CSL","markdown":{"yaml":{"title":"Harvard_Manchester_CSL"},"headingText":"Citation Syntax","containsRefs":false,"markdown":"\n\n\n### Authors\n\n#### No Author\n\nManchester Harvard Guidance:\n\n- If you cannot identify the author of a document use the title of the work italicised. \n\nInput:\n\n- ```@na2025 or [@na2025]```\n\nOutput:\n\n- @na2025 or [@na2025]\n\nIdeal:\n\n- *Some Book* (2025) or (*Some Book*, 2025)\n\n#### One Author\n\nManchester Harvard Guidance:\n\n- the surname of the author and the year of publication are stated as below.\n\nInput:\n\n- ```@bergelson_1996 or [@bergelson_1996]```\n\nOutput:\n\n- @bergelson_1996 or [@bergelson_1996]\n\nIdeal:\n\n- Bergelson (1996) or (Bergelson, 1996)\n\n#### Two Authors\n\nManchester Harvard Guidance:\n\n- the surnames of the authors, separated by ‘and’, and the year of publication are stated as below. \n\nInput:\n\n- ```@Bekka2000GroupActionDynamics or [@Bekka2000GroupActionDynamics]```\n\nOutput:\n\n- @Bekka2000GroupActionDynamics or [@Bekka2000GroupActionDynamics]\n\nIdeal:\n\n- Bekka and Mayer (2000) or (Bekka and Mayer, 2000)\n\n#### Three Authors\n\nManchester Harvard Guidance:\n\n- first author to penultimate author separated by commas. Penultimate author and last author separated by the word 'and'.\n\nInput:\n\n- ```@Moreira_2019 or [@Moreira_2019]```\n\nOutput:\n\n- @Moreira_2019 or [@Moreira_2019]\n\nIdeal:\n\n- Moreira, Richter and Robertson (2019) or (Moreira, Richter and Robertson, 2019)\n\n#### Four or more Authors\n\nManchester Harvard Guidance:\n\n- the surname of the first author, followed by ‘et al.’, and the year of publication are stated as below. \n\nInput:\n\n- ```@kra2023problems or [@kra2023problems]```\n\nOutput:\n\n- @kra2023problems or [@kra2023problems]\n\nIdeal:\n\n- Kra et al. (2023) or (Kra et al., 2023)\n\n#### Corporate Author\n\nManchester Harvard Guidance:\n\n- Spell out the full title of the corporation or organisation or use an acronym or Initialism if it is recognised as this.\n\nInput:\n\n- ```@bbc2025 or [@bbc2025]```\n\nOutput:\n\n- @bbc2025 or [@bbc2025]\n\nIdeal:\n\n- BBC (2025) or (BBC, 2025)\n\n#### No Date\n\nManchester Harvard Guidance:\n\n- The phrase “no date” should be used if you cannot identify a date of publication.\n\nInput:\n\n- ```@booknd or [@booknd]```\n\nOutput:\n\n- @booknd or [@booknd]\n\nIdeal:\n\n- Smith (no date) or (Smith, no date)\n\n#### Multiple Works by the same Author\n\nManchester Harvard Guidance:\n\n- If there are several works by one author (published in the same year) included in your Reference list entry, they should be differentiated by adding a lower case letter after the date. When referring to two or more sources by the same author in different years, you don’t need to repeat the author's surname in the citation. Include the surname and the oldest year first, then separate the rest with by semicolons (;) in chronological order starting with the oldest first\n\nInput:\n\n- ```@kra2022infinite did blah and then worked on blah [@kra2022proof; @kra2023problems].```\n\nOutput:\n\n- @kra2022infinite did blah and then worked on blah [@kra2022proof; @kra2023problems].\n\nIdeal:\n\n- Kra et al. (2022a) did blah and then worked on blah (Kra et al., 2022b; 2023).\n\nNote:\n\n- Sadly, CSL can only do commas between years for the same author. Fortunately, this is only a minor shortcoming.\n\n### Direct Citations\n\nManchester Harvard Guidance:\n\n- If the author’s name forms a natural part of your sentence, then you just need to note the relevant year (within parentheses) after the author(s) name.\n\n#### Standard Example\n\nInput:\n\n- ```@bergelson_1996 says blah.```\n\nOutput:\n\n- @bergelson_1996 says blah.\n\nIdeal:\n\n- Bergelson (1996) says blah.\n\n#### Standard Example with Locator\n\nInput:\n\n- ```@bergelson_1996 [pp. 2] says blah.```\n\nOutput:\n\n- @bergelson_1996 [pp. 2] says blah.\n\nIdeal:\n\n- Bergelson (1996, p. 2) says blah.\n\n#### Date Only\n\nInput:\n\n- ```Bergelson says blah [-@bergelson_1996].```\n\nOutput:\n\n- Bergelson says blah [-@bergelson_1996].\n\nIdeal:\n\n- Bergelson says blah (1996).\n\n#### No Parentheses\n\nInput:\n\n- ```Bergelson -@bergelson_1996 says Blah.```\n\nOutput:\n\n- Bergelson -@bergelson_1996 says Blah.\n\nIdeal:\n\n- Bergelson 1996 says blah.\n\n### Indirect Citations\n\nManchester Harvard Guidance:\n\n- If you do not mention the author’s name within your text, then place both the name and year in parentheses, at the end of the sentence.\n\n#### Standard Example\n\nInput:\n\n- ```Blah Blah [@bergelson_1996]. Blah Blah [@kra2023problems]```\n\nOutput:\n\n- Blah Blah [@bergelson_1996]. Blah Blah [@kra2023problems]\n\nIdeal:\n\n- Blah Blah (Bergelson, 1996). Blah Blah (Kra et al., 2023)\n\n#### Standard Example with Locator\n\nInput:\n\n- ```Blah Blah [@bergelson_1996, pp. 2]. Blah Blah [@kra2023problems, Section 1]```\n\nOutput:\n\n- Blah Blah [@bergelson_1996, pp. 2]. Blah Blah [@kra2023problems, Section 1]\n\nIdeal:\n\n- Blah Blah (Bergelson, 1996, p. 2). Blah Blah (Kra et al., 2023, Section 1)\n\n#### Authors supporting the same argument\n\nManchester Harvard Guidance:\n\n- Cite both names and separate with a semi-colon. List citations in chronological order (earliest date first) of year before surname, if the the citations are in the same year, then order in date then alphabetical order.\n\nInput:\n\n- ```Blah Blah [@bergelson_1996; @kra2023problems]```\n\nOutput:\n\n- Blah Blah [@bergelson_1996; @kra2023problems]\n\nIdeal:\n\n- Blah Blah (Bergelson, 1996; Kra et al., 2023)\n\n#### Authors supporting the same argument with Prefixes, Locators and Suffixes\n\nInput:\n\n- ```Blah Blah [see @bergelson_1996, pp. 2; and @kra2023problems, Theorem 2.2]```\n\nOutput:\n\n- Blah Blah [see @bergelson_1996, pp. 2; and @kra2023problems, Theorem 2.2]\n\nIdeal:\n\n- Blah Blah (see Bergelson, 1996, p. 2; and Kra et al., 2023, Theorem 2.2)\n\n#### Authors with the same surname\n\nManchester Harvard Guidance:\n\n- If two or more authors have the same surname then you need to provide more information to identify the source from which a quotation is taken. You should provide both author’s first initials (or even the authors' full name if different authors share initials) in your citation.\n\nInput:\n\n- ```Blah Blah [@prince2024; @prince2022; @prince2026]```\n\nOutput:\n\n- Blah Blah [@prince2024; @prince2022; @prince2026]\n\nIdeal:\n\n- Blah Blah (Kai Prince, 2022; Kira Prince, 2026; L. Prince, 2024)\n\n#### Citing sources from another source\n\nManchester Harvard Guidance:\n\n- When you wish to refer to a source that is cited or quoted in another authors work then you need to acknowledge this. This is known as indirect or secondary referencing. Use the term 'cited in' or 'quoted in' within your work. \n\nInput:\n\n- ```Blah Blah [Moreira, Richter and Robertson, 2019 cited in @kra2023problems]```\n\nOutput:\n\n- Blah Blah [Moreira, Richter and Robertson, 2019 cited in @kra2023problems]\n\nIdeal:\n\n- Blah Blah (Moreira, Richter and Robertson, 2019 cited in Kra et al., 2023)","srcMarkdownNoYaml":"\n\n## Citation Syntax\n\n### Authors\n\n#### No Author\n\nManchester Harvard Guidance:\n\n- If you cannot identify the author of a document use the title of the work italicised. \n\nInput:\n\n- ```@na2025 or [@na2025]```\n\nOutput:\n\n- @na2025 or [@na2025]\n\nIdeal:\n\n- *Some Book* (2025) or (*Some Book*, 2025)\n\n#### One Author\n\nManchester Harvard Guidance:\n\n- the surname of the author and the year of publication are stated as below.\n\nInput:\n\n- ```@bergelson_1996 or [@bergelson_1996]```\n\nOutput:\n\n- @bergelson_1996 or [@bergelson_1996]\n\nIdeal:\n\n- Bergelson (1996) or (Bergelson, 1996)\n\n#### Two Authors\n\nManchester Harvard Guidance:\n\n- the surnames of the authors, separated by ‘and’, and the year of publication are stated as below. \n\nInput:\n\n- ```@Bekka2000GroupActionDynamics or [@Bekka2000GroupActionDynamics]```\n\nOutput:\n\n- @Bekka2000GroupActionDynamics or [@Bekka2000GroupActionDynamics]\n\nIdeal:\n\n- Bekka and Mayer (2000) or (Bekka and Mayer, 2000)\n\n#### Three Authors\n\nManchester Harvard Guidance:\n\n- first author to penultimate author separated by commas. Penultimate author and last author separated by the word 'and'.\n\nInput:\n\n- ```@Moreira_2019 or [@Moreira_2019]```\n\nOutput:\n\n- @Moreira_2019 or [@Moreira_2019]\n\nIdeal:\n\n- Moreira, Richter and Robertson (2019) or (Moreira, Richter and Robertson, 2019)\n\n#### Four or more Authors\n\nManchester Harvard Guidance:\n\n- the surname of the first author, followed by ‘et al.’, and the year of publication are stated as below. \n\nInput:\n\n- ```@kra2023problems or [@kra2023problems]```\n\nOutput:\n\n- @kra2023problems or [@kra2023problems]\n\nIdeal:\n\n- Kra et al. (2023) or (Kra et al., 2023)\n\n#### Corporate Author\n\nManchester Harvard Guidance:\n\n- Spell out the full title of the corporation or organisation or use an acronym or Initialism if it is recognised as this.\n\nInput:\n\n- ```@bbc2025 or [@bbc2025]```\n\nOutput:\n\n- @bbc2025 or [@bbc2025]\n\nIdeal:\n\n- BBC (2025) or (BBC, 2025)\n\n#### No Date\n\nManchester Harvard Guidance:\n\n- The phrase “no date” should be used if you cannot identify a date of publication.\n\nInput:\n\n- ```@booknd or [@booknd]```\n\nOutput:\n\n- @booknd or [@booknd]\n\nIdeal:\n\n- Smith (no date) or (Smith, no date)\n\n#### Multiple Works by the same Author\n\nManchester Harvard Guidance:\n\n- If there are several works by one author (published in the same year) included in your Reference list entry, they should be differentiated by adding a lower case letter after the date. When referring to two or more sources by the same author in different years, you don’t need to repeat the author's surname in the citation. Include the surname and the oldest year first, then separate the rest with by semicolons (;) in chronological order starting with the oldest first\n\nInput:\n\n- ```@kra2022infinite did blah and then worked on blah [@kra2022proof; @kra2023problems].```\n\nOutput:\n\n- @kra2022infinite did blah and then worked on blah [@kra2022proof; @kra2023problems].\n\nIdeal:\n\n- Kra et al. (2022a) did blah and then worked on blah (Kra et al., 2022b; 2023).\n\nNote:\n\n- Sadly, CSL can only do commas between years for the same author. Fortunately, this is only a minor shortcoming.\n\n### Direct Citations\n\nManchester Harvard Guidance:\n\n- If the author’s name forms a natural part of your sentence, then you just need to note the relevant year (within parentheses) after the author(s) name.\n\n#### Standard Example\n\nInput:\n\n- ```@bergelson_1996 says blah.```\n\nOutput:\n\n- @bergelson_1996 says blah.\n\nIdeal:\n\n- Bergelson (1996) says blah.\n\n#### Standard Example with Locator\n\nInput:\n\n- ```@bergelson_1996 [pp. 2] says blah.```\n\nOutput:\n\n- @bergelson_1996 [pp. 2] says blah.\n\nIdeal:\n\n- Bergelson (1996, p. 2) says blah.\n\n#### Date Only\n\nInput:\n\n- ```Bergelson says blah [-@bergelson_1996].```\n\nOutput:\n\n- Bergelson says blah [-@bergelson_1996].\n\nIdeal:\n\n- Bergelson says blah (1996).\n\n#### No Parentheses\n\nInput:\n\n- ```Bergelson -@bergelson_1996 says Blah.```\n\nOutput:\n\n- Bergelson -@bergelson_1996 says Blah.\n\nIdeal:\n\n- Bergelson 1996 says blah.\n\n### Indirect Citations\n\nManchester Harvard Guidance:\n\n- If you do not mention the author’s name within your text, then place both the name and year in parentheses, at the end of the sentence.\n\n#### Standard Example\n\nInput:\n\n- ```Blah Blah [@bergelson_1996]. Blah Blah [@kra2023problems]```\n\nOutput:\n\n- Blah Blah [@bergelson_1996]. Blah Blah [@kra2023problems]\n\nIdeal:\n\n- Blah Blah (Bergelson, 1996). Blah Blah (Kra et al., 2023)\n\n#### Standard Example with Locator\n\nInput:\n\n- ```Blah Blah [@bergelson_1996, pp. 2]. Blah Blah [@kra2023problems, Section 1]```\n\nOutput:\n\n- Blah Blah [@bergelson_1996, pp. 2]. Blah Blah [@kra2023problems, Section 1]\n\nIdeal:\n\n- Blah Blah (Bergelson, 1996, p. 2). Blah Blah (Kra et al., 2023, Section 1)\n\n#### Authors supporting the same argument\n\nManchester Harvard Guidance:\n\n- Cite both names and separate with a semi-colon. List citations in chronological order (earliest date first) of year before surname, if the the citations are in the same year, then order in date then alphabetical order.\n\nInput:\n\n- ```Blah Blah [@bergelson_1996; @kra2023problems]```\n\nOutput:\n\n- Blah Blah [@bergelson_1996; @kra2023problems]\n\nIdeal:\n\n- Blah Blah (Bergelson, 1996; Kra et al., 2023)\n\n#### Authors supporting the same argument with Prefixes, Locators and Suffixes\n\nInput:\n\n- ```Blah Blah [see @bergelson_1996, pp. 2; and @kra2023problems, Theorem 2.2]```\n\nOutput:\n\n- Blah Blah [see @bergelson_1996, pp. 2; and @kra2023problems, Theorem 2.2]\n\nIdeal:\n\n- Blah Blah (see Bergelson, 1996, p. 2; and Kra et al., 2023, Theorem 2.2)\n\n#### Authors with the same surname\n\nManchester Harvard Guidance:\n\n- If two or more authors have the same surname then you need to provide more information to identify the source from which a quotation is taken. You should provide both author’s first initials (or even the authors' full name if different authors share initials) in your citation.\n\nInput:\n\n- ```Blah Blah [@prince2024; @prince2022; @prince2026]```\n\nOutput:\n\n- Blah Blah [@prince2024; @prince2022; @prince2026]\n\nIdeal:\n\n- Blah Blah (Kai Prince, 2022; Kira Prince, 2026; L. Prince, 2024)\n\n#### Citing sources from another source\n\nManchester Harvard Guidance:\n\n- When you wish to refer to a source that is cited or quoted in another authors work then you need to acknowledge this. This is known as indirect or secondary referencing. Use the term 'cited in' or 'quoted in' within your work. \n\nInput:\n\n- ```Blah Blah [Moreira, Richter and Robertson, 2019 cited in @kra2023problems]```\n\nOutput:\n\n- Blah Blah [Moreira, Richter and Robertson, 2019 cited in @kra2023problems]\n\nIdeal:\n\n- Blah Blah (Moreira, Richter and Robertson, 2019 cited in Kra et al., 2023)"},"formats":{"html":{"identifier":{"display-name":"HTML","target-format":"html","base-format":"html"},"execute":{"fig-width":7,"fig-height":5,"fig-format":"retina","fig-dpi":96,"df-print":"default","error":false,"eval":true,"cache":null,"freeze":false,"echo":true,"output":true,"warning":true,"include":true,"keep-md":false,"keep-ipynb":false,"ipynb":null,"enabled":null,"daemon":null,"daemon-restart":false,"debug":false,"ipynb-filters":[],"ipynb-shell-interactivity":null,"plotly-connected":true,"engine":"markdown"},"render":{"keep-tex":false,"keep-typ":false,"keep-source":false,"keep-hidden":false,"prefer-html":false,"output-divs":true,"output-ext":"html","fig-align":"default","fig-pos":null,"fig-env":null,"code-fold":"none","code-overflow":"scroll","code-link":false,"code-line-numbers":false,"code-tools":false,"tbl-colwidths":"auto","merge-includes":true,"inline-includes":false,"preserve-yaml":false,"latex-auto-mk":true,"latex-auto-install":true,"latex-clean":true,"latex-min-runs":1,"latex-max-runs":10,"latex-makeindex":"makeindex","latex-makeindex-opts":[],"latex-tlmgr-opts":[],"latex-input-paths":[],"latex-output-dir":null,"link-external-icon":false,"link-external-newwindow":false,"self-contained-math":false,"format-resources":[],"notebook-links":true},"pandoc":{"standalone":true,"wrap":"none","default-image-extension":"png","to":"html","output-file":"index.html"},"language":{"toc-title-document":"Table of contents","toc-title-website":"On this page","related-formats-title":"Other Formats","related-notebooks-title":"Notebooks","source-notebooks-prefix":"Source","other-links-title":"Other Links","code-links-title":"Code Links","launch-dev-container-title":"Launch Dev Container","launch-binder-title":"Launch Binder","article-notebook-label":"Article Notebook","notebook-preview-download":"Download Notebook","notebook-preview-download-src":"Download Source","notebook-preview-back":"Back to Article","manuscript-meca-bundle":"MECA Bundle","section-title-abstract":"Abstract","section-title-appendices":"Appendices","section-title-footnotes":"Footnotes","section-title-references":"References","section-title-reuse":"Reuse","section-title-copyright":"Copyright","section-title-citation":"Citation","appendix-attribution-cite-as":"For attribution, please cite this work as:","appendix-attribution-bibtex":"BibTeX citation:","appendix-view-license":"View License","title-block-author-single":"Author","title-block-author-plural":"Authors","title-block-affiliation-single":"Affiliation","title-block-affiliation-plural":"Affiliations","title-block-published":"Published","title-block-modified":"Modified","title-block-keywords":"Keywords","callout-tip-title":"Tip","callout-note-title":"Note","callout-warning-title":"Warning","callout-important-title":"Important","callout-caution-title":"Caution","code-summary":"Code","code-tools-menu-caption":"Code","code-tools-show-all-code":"Show All Code","code-tools-hide-all-code":"Hide All Code","code-tools-view-source":"View Source","code-tools-source-code":"Source Code","tools-share":"Share","tools-download":"Download","code-line":"Line","code-lines":"Lines","copy-button-tooltip":"Copy to Clipboard","copy-button-tooltip-success":"Copied!","repo-action-links-edit":"Edit this page","repo-action-links-source":"View source","repo-action-links-issue":"Report an issue","back-to-top":"Back to top","search-no-results-text":"No results","search-matching-documents-text":"matching documents","search-copy-link-title":"Copy link to search","search-hide-matches-text":"Hide additional matches","search-more-match-text":"more match in this document","search-more-matches-text":"more matches in this document","search-clear-button-title":"Clear","search-text-placeholder":"","search-detached-cancel-button-title":"Cancel","search-submit-button-title":"Submit","search-label":"Search","toggle-section":"Toggle section","toggle-sidebar":"Toggle sidebar navigation","toggle-dark-mode":"Toggle dark mode","toggle-reader-mode":"Toggle reader mode","toggle-navigation":"Toggle navigation","crossref-fig-title":"Figure","crossref-tbl-title":"Table","crossref-lst-title":"Listing","crossref-thm-title":"Theorem","crossref-lem-title":"Lemma","crossref-cor-title":"Corollary","crossref-prp-title":"Proposition","crossref-cnj-title":"Conjecture","crossref-def-title":"Definition","crossref-exm-title":"Example","crossref-exr-title":"Exercise","crossref-ch-prefix":"Chapter","crossref-apx-prefix":"Appendix","crossref-sec-prefix":"Section","crossref-eq-prefix":"Equation","crossref-lof-title":"List of Figures","crossref-lot-title":"List of Tables","crossref-lol-title":"List of Listings","environment-proof-title":"Proof","environment-remark-title":"Remark","environment-solution-title":"Solution","listing-page-order-by":"Order By","listing-page-order-by-default":"Default","listing-page-order-by-date-asc":"Oldest","listing-page-order-by-date-desc":"Newest","listing-page-order-by-number-desc":"High to Low","listing-page-order-by-number-asc":"Low to High","listing-page-field-date":"Date","listing-page-field-title":"Title","listing-page-field-description":"Description","listing-page-field-author":"Author","listing-page-field-filename":"File Name","listing-page-field-filemodified":"Modified","listing-page-field-subtitle":"Subtitle","listing-page-field-readingtime":"Reading Time","listing-page-field-wordcount":"Word Count","listing-page-field-categories":"Categories","listing-page-minutes-compact":"{0} min","listing-page-category-all":"All","listing-page-no-matches":"No matching items","listing-page-words":"{0} words","listing-page-filter":"Filter","draft":"Draft"},"metadata":{"lang":"en","fig-responsive":true,"quarto-version":"1.7.32","csl":"harvard-manchester.csl","bibliography":["references.bib"],"link-citations":false,"title":"Harvard_Manchester_CSL"},"extensions":{"book":{"multiFile":true}}}},"projectFormats":["html"]}